geeplot/__init__.py
geeplot/py.typed
geeplot-0.0.0.dist-info/METADATA
geeplot-0.0.0.dist-info/WHEEL
geeplot-0.0.0.dist-info/licenses/AUTHORS.rst
geeplot-0.0.0.dist-info/licenses/LICENSE
geeplot-0.0.0.dist-info/RECORD
