Metadata-Version: 2.4
Name: geeplot
Version: 0.0.0
Summary: A python library to bridge GEE computation capabilities and all the Python plotting solutions
Project-URL: Homepage, https://github.com/gee-community/geeplot
Author-email: Pierrick Rambaud <pierrick.rambaud49@gmail.com>
License: MIT
License-File: AUTHORS.rst
License-File: LICENSE
Keywords: Python,skeleton
Classifier: Development Status :: 3 - Alpha
Classifier: Intended Audience :: Developers
Classifier: License :: OSI Approved :: MIT License
Classifier: Programming Language :: Python :: 3.8
Classifier: Programming Language :: Python :: 3.9
Classifier: Programming Language :: Python :: 3.10
Classifier: Programming Language :: Python :: 3.11
Requires-Python: >=3.8
Requires-Dist: deprecated>=1.2.14
Provides-Extra: doc
Requires-Dist: pydata-sphinx-theme; extra == 'doc'
Requires-Dist: sphinx-autoapi; extra == 'doc'
Requires-Dist: sphinx-copybutton; extra == 'doc'
Requires-Dist: sphinx-design; extra == 'doc'
Requires-Dist: sphinx>=6.2.1; extra == 'doc'
Provides-Extra: test
Requires-Dist: pytest; extra == 'test'
Requires-Dist: pytest-cov; extra == 'test'
Requires-Dist: pytest-deadfixtures; extra == 'test'
